{"lastUpdate":1729535419360,"clubs":{},"paths":[{"name":"Boys Schools U18 Tier 2 Finals 2024","path":"ics/eh/per-competition/407.ics","type":"competition","index":11,"count":2},{"name":"Boys Schools U14 Tier 1 Finals 2024","path":"ics/eh/per-competition/409.ics","type":"competition","index":12,"count":2},{"name":"UK Girls School Games 2024","path":"ics/eh/per-competition/425.ics","type":"competition","index":1,"count":9},{"name":"UK Boys School Games 2024","path":"ics/eh/per-competition/424.ics","type":"competition","index":0,"count":9},{"name":"Boys Schools U16 Tier 1 Finals 2024","path":"ics/eh/per-competition/410.ics","type":"competition","index":13,"count":5},{"name":"Boys Clubs U12 In2 Finals 2024","path":"ics/eh/per-competition/405.ics","type":"competition","index":5,"count":16},{"name":"Junior Club U14 Championships","path":"ics/eh/per-competition/417.ics","type":"competition","index":10,"count":10},{"name":"Girls Clubs U12 In2 Finals 2024","path":"ics/eh/per-competition/406.ics","type":"competition","index":6,"count":16},{"name":"Club Championships Finals Weekend 2023/24","path":"ics/eh/per-competition/415.ics","type":"competition","index":9,"count":18},{"name":"Girls Schools U13 In2 Finals 2024","path":"ics/eh/per-competition/403.ics","type":"competition","index":7,"count":16},{"name":"Boys Schools U13 In2 Finals 2024","path":"ics/eh/per-competition/404.ics","type":"competition","index":8,"count":16},{"name":"Junior Club U14 Supra League","path":"ics/eh/per-competition/418.ics","type":"competition","index":4,"count":32},{"name":"Boys Talent Academy Cup","path":"ics/eh/per-competition/422.ics","type":"competition","index":3,"count":48},{"name":"Girls Talent Academy Cup","path":"ics/eh/per-competition/421.ics","type":"competition","index":2,"count":48},{"name":"All EH mens's matches","path":"ics/eh/mens-matches.ics","type":"total","index":-1,"count":98},{"name":"All EH women's matches","path":"ics/eh/womens-matches.ics","type":"total","index":-1,"count":89},{"name":"All EH mixed matches","path":"ics/eh/mixed-matches.ics","type":"total","index":-1,"count":60},{"name":"All EH matches","path":"ics/eh/all-matches.ics","type":"total","index":-2,"count":247}]}